pg_idempotent/__init__.py
pg_idempotent/cli.py
pg_idempotent/analyzer/__init__.py
pg_idempotent/analyzer/rustworkx_analyzer.py
pg_idempotent/cli_/__init__.py
pg_idempotent/naming/__init__.py
pg_idempotent/naming/llm_namer.py
pg_idempotent/parser/__init__.py
pg_idempotent/parser/parser.py
pg_idempotent/plugins/__init__.py
pg_idempotent/plugins/base.py
pg_idempotent/plugins/loader.py
pg_idempotent/splitter/__init__.py
pg_idempotent/splitter/schema_splitter.py
pg_idempotent/transformer/__init__.py
pg_idempotent/transformer/templates.py
pg_idempotent/transformer/transformer.py
pg_idempotent/utils/__init__.py
pg_idempotent/utils/file_utils.py
pg_idempotent/validator/__init__.py
pg_idempotent/validator/migra_validator.py
pg_idempotent-0.2.0.dist-info/METADATA
pg_idempotent-0.2.0.dist-info/WHEEL
pg_idempotent-0.2.0.dist-info/entry_points.txt
pg_idempotent-0.2.0.dist-info/RECORD
