Metadata-Version: 2.4
Name: pg-idempotent
Version: 0.2.0
Summary: Transform PostgreSQL migrations into idempotent versions that can be run multiple times without errors. Includes native Supabase integration.
Project-URL: homepage, https://github.com/kivo360/pg-idempotent
Project-URL: source, https://github.com/kivo360/pg-idempotent
Project-URL: changelog, https://github.com/kivo360/pg-idempotent/blob/main/CHANGELOG.md
Project-URL: releasenotes, https://github.com/kivo360/pg-idempotent/releases
Project-URL: documentation, https://github.com/kivo360/pg-idempotent
Project-URL: issues, https://github.com/kivo360/pg-idempotent/issues
Author-email: Kevin Hill <kah.kevin.hill@gmail.com>
License: MIT
Keywords: idempotent,migrations,postgresql,sql,supabase
Classifier: Development Status :: 4 - Beta
Classifier: Intended Audience :: Developers
Classifier: License :: OSI Approved :: MIT License
Classifier: Programming Language :: Python :: 3
Classifier: Programming Language :: Python :: 3.10
Classifier: Programming Language :: Python :: 3.11
Classifier: Programming Language :: Python :: 3.12
Classifier: Topic :: Database
Classifier: Topic :: Software Development :: Libraries :: Python Modules
Requires-Python: <4.0,>=3.10
Requires-Dist: pglast>=6.0
Requires-Dist: requests>=2.31.0
Requires-Dist: rich>=13.0
Requires-Dist: typer>=0.15.1
Provides-Extra: advanced
Requires-Dist: aiohttp>=3.9.0; extra == 'advanced'
Requires-Dist: fireworks-ai>=0.16.0; extra == 'advanced'
Requires-Dist: migra>=3.0.0; extra == 'advanced'
Requires-Dist: openai>=1.0.0; extra == 'advanced'
Requires-Dist: rustworkx>=0.14.0; extra == 'advanced'
Requires-Dist: sqlalchemy>=2.0.0; extra == 'advanced'
Provides-Extra: all
Requires-Dist: aiohttp>=3.9.0; extra == 'all'
Requires-Dist: fireworks-ai>=0.16.0; extra == 'all'
Requires-Dist: migra>=3.0.0; extra == 'all'
Requires-Dist: openai>=1.0.0; extra == 'all'
Requires-Dist: rustworkx>=0.14.0; extra == 'all'
Requires-Dist: sqlalchemy>=2.0.0; extra == 'all'
